otel_cli/__init__.py
otel_cli/cli.py
otel_cli/cli_helpers.py
otel_cli/compat.py
otel_cli/otel.py
otel_cli/utils.py
otel_cli-0.4.0.dist-info/entry_points.txt
otel_cli-0.4.0.dist-info/LICENSE
otel_cli-0.4.0.dist-info/WHEEL
otel_cli-0.4.0.dist-info/METADATA
otel_cli-0.4.0.dist-info/RECORD
