Metadata-Version: 2.1
Name: otel-cli
Version: 0.4.0
Summary: CLI for OpenTelemetry Traces and Metrics in Python
Author: Moshi Binyamini
Author-email: moshi.binyamini@dell.com
Requires-Python: >=3.7,<4.0
Classifier: Development Status :: 3 - Alpha
Classifier: Environment :: Console
Classifier: Intended Audience :: Developers
Classifier: Natural Language :: English
Classifier: Programming Language :: Python :: 3
Classifier: Programming Language :: Python :: 3.7
Classifier: Programming Language :: Python :: 3.8
Classifier: Programming Language :: Python :: 3.9
Classifier: Programming Language :: Python :: 3.10
Classifier: Programming Language :: Python :: 3.11
Classifier: Programming Language :: Python :: 3
Classifier: Programming Language :: Python :: 3.10
Classifier: Programming Language :: Python :: 3.11
Classifier: Programming Language :: Python :: 3.7
Classifier: Programming Language :: Python :: 3.8
Classifier: Programming Language :: Python :: 3.9
Classifier: Topic :: System :: Monitoring
Classifier: Topic :: Utilities
Requires-Dist: Click (>=8.1,<9.0)
Requires-Dist: opentelemetry-exporter-otlp (>=1.14.0,<1.15.0)
Requires-Dist: opentelemetry-proto (>=1.14.0,<1.15.0)
Requires-Dist: opentelemetry-sdk (>=1.14.0,<1.15.0)
Requires-Dist: typing-extensions (>=4.4.0,<4.5.0); python_version < "3.8"
